scrapera/__init__.py
scrapera/__pycache__/__init__.cpython-37.pyc
scrapera/audio/__init__.py
scrapera/audio/youtube_playlist_scraper.py
scrapera/image/__init__.py
scrapera/image/duckduckgo.py
scrapera/image/giphy.py
scrapera/image/tumblr.py
scrapera/miscellaneous/__init__.py
scrapera/miscellaneous/yahoo_stocks.py
scrapera/text/__init__.py
scrapera/text/amazon.py
scrapera/text/imdb.py
scrapera/text/reddit.py
scrapera/text/scroll_news.py
scrapera/text/voice_of_america.py
scrapera/video/__init__.py
scrapera/video/vimeo.py
scrapera/video/youtube.py
scrapera-1.1.3.dist-info/LICENSE
scrapera-1.1.3.dist-info/METADATA
scrapera-1.1.3.dist-info/WHEEL
scrapera-1.1.3.dist-info/top_level.txt
scrapera-1.1.3.dist-info/RECORD
