Metadata-Version: 2.1
Name: scrapera
Version: 1.1.3
Summary: A universal package of scraper scripts for humans
Home-page: https://github.com/DarshanDeshpande/Scrapera
Author: Darshan Deshpande
Author-email: darshan1504@gmail.com
License: MIT
Platform: UNKNOWN
Classifier: Development Status :: 5 - Production/Stable
Classifier: License :: OSI Approved :: MIT License
Classifier: Programming Language :: Python :: 3.6
Classifier: Programming Language :: Python :: 3.7
Classifier: Programming Language :: Python :: 3.8
Requires-Python: >=3.6.0
Requires-Dist: bs4
Requires-Dist: beautifulsoup4
Requires-Dist: certifi
Requires-Dist: chardet
Requires-Dist: idna
Requires-Dist: Pillow
Requires-Dist: python-dateutil
Requires-Dist: pytube
Requires-Dist: pytz
Requires-Dist: six
Requires-Dist: soupsieve
Requires-Dist: tqdm
Requires-Dist: typing-extensions
Requires-Dist: urllib3
Requires-Dist: lxml
Requires-Dist: requests
Requires-Dist: brotli
Requires-Dist: aiohttp
Requires-Dist: aiosqlite
Requires-Dist: aiofiles
